Metadata-Version: 2.1
Name: odoo14-addon-hr-expense-advance-clearing-sequence
Version: 14.0.1.0.1.dev8
Summary: HR Expense Advance Clearing Sequence
Home-page: https://github.com/OCA/hr-expense
Author: Ecosoft, Odoo Community Association (OCA)
Author-email: support@odoo-community.org
License: AGPL-3
Platform: UNKNOWN
Classifier: Programming Language :: Python
Classifier: Framework :: Odoo
Classifier: Framework :: Odoo :: 14.0
Classifier: License :: OSI Approved :: GNU Affero General Public License v3
Requires-Python: >=3.6
Requires-Dist: odoo14-addon-hr-expense-advance-clearing
Requires-Dist: odoo14-addon-hr-expense-sequence
Requires-Dist: odoo <14.1dev,>=14.0a
